{
  "fetched_at": "2026-04-13T22:09:42.615042",
  "items": [
    {
      "title": "【6555 榮炭】更正公告本公司董事會決議召開114年股東常會召集相關事宜",
      "summary": "",
      "published": "04/13 20:18",
      "link": "https://mops.twse.com.tw/mops/#/web/t05sr01_1",
      "is_revenue": false,
      "source": "mops"
    },
    {
      "title": "【7902 宇越生醫】本公司董事會決議不發放股利",
      "summary": "",
      "published": "04/13 19:33",
      "link": "https://mops.twse.com.tw/mops/#/web/t05sr01_1",
      "is_revenue": false,
      "source": "mops"
    },
    {
      "title": "【7902 宇越生醫】公告本公司董事會決議召開115年股東常會相關事宜(新增議案)",
      "summary": "",
      "published": "04/13 19:32",
      "link": "https://mops.twse.com.tw/mops/#/web/t05sr01_1",
      "is_revenue": false,
      "source": "mops"
    },
    {
      "title": "【9103 美德醫療-DR】114年度及113年度財務報告暨會計師複核報告",
      "summary": "",
      "published": "04/13 19:21",
      "link": "https://mops.twse.com.tw/mops/#/web/t05sr01_1",
      "is_revenue": false,
      "source": "mops"
    },
    {
      "title": "【9103 美德醫療-DR】股東常會通知附錄-更新股份購回授權提案-英文版",
      "summary": "",
      "published": "04/13 19:20",
      "link": "https://mops.twse.com.tw/mops/#/web/t05sr01_1",
      "is_revenue": false,
      "source": "mops"
    },
    {
      "title": "【9103 美德醫療-DR】股東常會通知附錄-更新股份購回授權提案-中文版",
      "summary": "",
      "published": "04/13 19:20",
      "link": "https://mops.twse.com.tw/mops/#/web/t05sr01_1",
      "is_revenue": false,
      "source": "mops"
    },
    {
      "title": "【9103 美德醫療-DR】年度股東常會開會通知之公告-英文版",
      "summary": "",
      "published": "04/13 19:19",
      "link": "https://mops.twse.com.tw/mops/#/web/t05sr01_1",
      "is_revenue": false,
      "source": "mops"
    },
    {
      "title": "【9103 美德醫療-DR】年度股東常會開會通知之公告-中文版",
      "summary": "",
      "published": "04/13 19:19",
      "link": "https://mops.twse.com.tw/mops/#/web/t05sr01_1",
      "is_revenue": false,
      "source": "mops"
    },
    {
      "title": "【2883 凱基金】公告本公司暨主要子公司115年3月份自結合併盈餘",
      "summary": "",
      "published": "04/13 19:10",
      "link": "https://mops.twse.com.tw/mops/#/web/t05sr01_1",
      "is_revenue": true,
      "source": "mops"
    },
    {
      "title": "【3290 東浦】公告本公司預計通過115年第1季財務報告董事會召開日期",
      "summary": "",
      "published": "04/13 19:03",
      "link": "https://mops.twse.com.tw/mops/#/web/t05sr01_1",
      "is_revenue": false,
      "source": "mops"
    },
    {
      "title": "【2371 大同】公告董事會決議本公司民國115年股東常會相關事宜(新增議案)\n-配合電子投票系統，刪除新增字樣",
      "summary": "",
      "published": "04/13 18:55",
      "link": "https://mops.twse.com.tw/mops/#/web/t05sr01_1",
      "is_revenue": false,
      "source": "mops"
    },
    {
      "title": "【6618 永虹先進】本公司董事會通過113年度合併財務報告",
      "summary": "",
      "published": "04/13 18:54",
      "link": "https://mops.twse.com.tw/mops/#/web/t05sr01_1",
      "is_revenue": false,
      "source": "mops"
    },
    {
      "title": "【2438 翔耀】(更新)115年股東常會\n(股東會紀念品發放事宜補行公告)",
      "summary": "",
      "published": "04/13 18:33",
      "link": "https://mops.twse.com.tw/mops/#/web/t05sr01_1",
      "is_revenue": false,
      "source": "mops"
    },
    {
      "title": "【3630 新鉅科】修正本公司114年度合併/個體財報報告附註之資金貸與他人事項。",
      "summary": "",
      "published": "04/13 18:15",
      "link": "https://mops.twse.com.tw/mops/#/web/t05sr01_1",
      "is_revenue": false,
      "source": "mops"
    },
    {
      "title": "【6618 永虹先進】董事會決議不分派股利",
      "summary": "",
      "published": "04/13 18:15",
      "link": "https://mops.twse.com.tw/mops/#/web/t05sr01_1",
      "is_revenue": false,
      "source": "mops"
    },
    {
      "title": "【6959 兆捷科技】公告本公司董事會決議召開115年股東常會(新增議案)",
      "summary": "",
      "published": "04/13 18:07",
      "link": "https://mops.twse.com.tw/mops/#/web/t05sr01_1",
      "is_revenue": false,
      "source": "mops"
    },
    {
      "title": "【6959 兆捷科技】公告本公司董事會決議不分派股利",
      "summary": "",
      "published": "04/13 18:03",
      "link": "https://mops.twse.com.tw/mops/#/web/t05sr01_1",
      "is_revenue": false,
      "source": "mops"
    },
    {
      "title": "【5529 鉅陞】公告本公司115年股東常會重要決議事項",
      "summary": "",
      "published": "04/13 18:01",
      "link": "https://mops.twse.com.tw/mops/#/web/t05sr01_1",
      "is_revenue": false,
      "source": "mops"
    },
    {
      "title": "【6959 兆捷科技】公告本公司董事會決議通過114年度個體暨合併財務報告",
      "summary": "",
      "published": "04/13 17:55",
      "link": "https://mops.twse.com.tw/mops/#/web/t05sr01_1",
      "is_revenue": false,
      "source": "mops"
    },
    {
      "title": "【1104 環泥】公告本公司115年第1季財務報告提報之董事會召開日期",
      "summary": "",
      "published": "04/13 17:42",
      "link": "https://mops.twse.com.tw/mops/#/web/t05sr01_1",
      "is_revenue": false,
      "source": "mops"
    },
    {
      "title": "【6842 瑞宇】公告本公司董事會通過114年度合併財務報告(更正)",
      "summary": "",
      "published": "04/13 17:34",
      "link": "https://mops.twse.com.tw/mops/#/web/t05sr01_1",
      "is_revenue": false,
      "source": "mops"
    },
    {
      "title": "【6842 瑞宇】公告本公司董事會決議114年度盈餘轉增資發行新股",
      "summary": "",
      "published": "04/13 17:32",
      "link": "https://mops.twse.com.tw/mops/#/web/t05sr01_1",
      "is_revenue": false,
      "source": "mops"
    },
    {
      "title": "【3576 聯合再生】本公司董事會決議召開115年股東常會公告(增列議案)",
      "summary": "",
      "published": "04/13 17:31",
      "link": "https://mops.twse.com.tw/mops/#/web/t05sr01_1",
      "is_revenue": false,
      "source": "mops"
    },
    {
      "title": "【2308 台達電】本公司代子公司Delta Electronics Int'l (Singapore)\r\nPte. Ltd.公告現金股利除息基準日",
      "summary": "",
      "published": "04/13 17:28",
      "link": "https://mops.twse.com.tw/mops/#/web/t05sr01_1",
      "is_revenue": false,
      "source": "mops"
    },
    {
      "title": "【6842 瑞宇】公告本公司董事會決議114年度股利分派情形",
      "summary": "",
      "published": "04/13 17:28",
      "link": "https://mops.twse.com.tw/mops/#/web/t05sr01_1",
      "is_revenue": false,
      "source": "mops"
    },
    {
      "title": "【2308 台達電】本公司代子公司Delta Electronics Int'l (Singapore)\r\nPte. Ltd.公告發放現金股利",
      "summary": "",
      "published": "04/13 17:25",
      "link": "https://mops.twse.com.tw/mops/#/web/t05sr01_1",
      "is_revenue": false,
      "source": "mops"
    },
    {
      "title": "【6886 遠東生技】公告本公司董事會決議召開115年股東常會",
      "summary": "",
      "published": "04/13 17:25",
      "link": "https://mops.twse.com.tw/mops/#/web/t05sr01_1",
      "is_revenue": false,
      "source": "mops"
    },
    {
      "title": "【5269 祥碩】董事會決議股利分派",
      "summary": "",
      "published": "04/13 17:24",
      "link": "https://mops.twse.com.tw/mops/#/web/t05sr01_1",
      "is_revenue": false,
      "source": "mops"
    },
    {
      "title": "【6842 瑞宇】公告本公司董事會決議召開115年股東常會(新增議案)",
      "summary": "",
      "published": "04/13 17:20",
      "link": "https://mops.twse.com.tw/mops/#/web/t05sr01_1",
      "is_revenue": false,
      "source": "mops"
    },
    {
      "title": "【1626 艾美特-KY】更正-公告本公司董事會決議2025年股東常會召開案\n(更正召集事由順序)",
      "summary": "",
      "published": "04/13 17:19",
      "link": "https://mops.twse.com.tw/mops/#/web/t05sr01_1",
      "is_revenue": false,
      "source": "mops"
    },
    {
      "title": "【2065 世豐】更正本公司115年3月營收公告",
      "summary": "",
      "published": "04/13 17:16",
      "link": "https://mops.twse.com.tw/mops/#/web/t05sr01_1",
      "is_revenue": true,
      "source": "mops"
    },
    {
      "title": "【2465 麗臺】修正本公司董事會決議115年股東常會召集事由",
      "summary": "",
      "published": "04/13 17:13",
      "link": "https://mops.twse.com.tw/mops/#/web/t05sr01_1",
      "is_revenue": false,
      "source": "mops"
    },
    {
      "title": "【5269 祥碩】本公司董事會通過增列115年股東常會召集事由",
      "summary": "",
      "published": "04/13 17:01",
      "link": "https://mops.twse.com.tw/mops/#/web/t05sr01_1",
      "is_revenue": false,
      "source": "mops"
    },
    {
      "title": "【2885 元大金】元大金控公告115年3月份自結合併損益",
      "summary": "",
      "published": "04/13 17:00",
      "link": "https://mops.twse.com.tw/mops/#/web/t05sr01_1",
      "is_revenue": true,
      "source": "mops"
    },
    {
      "title": "【2328 廣宇】公告董事會決議股利分派",
      "summary": "",
      "published": "04/13 17:00",
      "link": "https://mops.twse.com.tw/mops/#/web/t05sr01_1",
      "is_revenue": false,
      "source": "mops"
    },
    {
      "title": "【4916 事欣科】公告本公司董事會決議召開115年股東常會事宜\n(配合電子投票系統修正召集事由)",
      "summary": "",
      "published": "04/13 16:59",
      "link": "https://mops.twse.com.tw/mops/#/web/t05sr01_1",
      "is_revenue": false,
      "source": "mops"
    },
    {
      "title": "【4529 淳紳】本公司辦理減資彌補虧損致債權人公告。\r\n協議書之增補協議。",
      "summary": "",
      "published": "04/13 16:53",
      "link": "https://mops.twse.com.tw/mops/#/web/t05sr01_1",
      "is_revenue": false,
      "source": "mops"
    },
    {
      "title": "【7891 博研醫藥】本公司董事會決議召開115年股東常會相關事宜",
      "summary": "",
      "published": "04/13 16:52",
      "link": "https://mops.twse.com.tw/mops/#/web/t05sr01_1",
      "is_revenue": false,
      "source": "mops"
    },
    {
      "title": "【2006 東和鋼鐵】代重要子公司東鋼鋼結構股份有限公司公告\r\n115年股東常會解除董事競業之限制",
      "summary": "",
      "published": "04/13 16:33",
      "link": "https://mops.twse.com.tw/mops/#/web/t05sr01_1",
      "is_revenue": false,
      "source": "mops"
    },
    {
      "title": "【2006 東和鋼鐵】代重要子公司東鋼鋼結構股份有限公司公告115年股東常會\r\n董監事改選當選名單",
      "summary": "",
      "published": "04/13 16:31",
      "link": "https://mops.twse.com.tw/mops/#/web/t05sr01_1",
      "is_revenue": false,
      "source": "mops"
    },
    {
      "title": "【7904 任開數位】公告本公司董事會決議股利分派情形",
      "summary": "",
      "published": "04/13 16:29",
      "link": "https://mops.twse.com.tw/mops/#/web/t05sr01_1",
      "is_revenue": false,
      "source": "mops"
    },
    {
      "title": "【2006 東和鋼鐵】代重要子公司東鋼鋼結構股份有限公司公告\r\n115年股東常會重要決議事項",
      "summary": "",
      "published": "04/13 16:28",
      "link": "https://mops.twse.com.tw/mops/#/web/t05sr01_1",
      "is_revenue": false,
      "source": "mops"
    },
    {
      "title": "【6761 穩得】補充公告本公司董事會通過115年股東常會召開相關事宜\n(增列召集事由)",
      "summary": "",
      "published": "04/13 16:26",
      "link": "https://mops.twse.com.tw/mops/#/web/t05sr01_1",
      "is_revenue": false,
      "source": "mops"
    },
    {
      "title": "【8272 全景軟體】公告本公司董事會決議召開115年度股東常會相關事宜\n(新增/修正討論事項)",
      "summary": "",
      "published": "04/13 16:18",
      "link": "https://mops.twse.com.tw/mops/#/web/t05sr01_1",
      "is_revenue": false,
      "source": "mops"
    },
    {
      "title": "【2939 永邑-KY】更正本公司114年合併財報(含iXBRL)部份內容",
      "summary": "",
      "published": "04/13 16:15",
      "link": "https://mops.twse.com.tw/mops/#/web/t05sr01_1",
      "is_revenue": false,
      "source": "mops"
    },
    {
      "title": "【3349 寶德】公告本公司董事會決議不分配股利",
      "summary": "",
      "published": "04/13 16:13",
      "link": "https://mops.twse.com.tw/mops/#/web/t05sr01_1",
      "is_revenue": false,
      "source": "mops"
    },
    {
      "title": "【2884 玉山金】本公司代子公司玉山證券公告114年度盈餘分配案之現金股利\r\n除息基準日",
      "summary": "",
      "published": "04/13 16:10",
      "link": "https://mops.twse.com.tw/mops/#/web/t05sr01_1",
      "is_revenue": false,
      "source": "mops"
    },
    {
      "title": "【5222 全訊】補充說明本公司於民國115年4月8日法說會之內容",
      "summary": "",
      "published": "04/13 16:03",
      "link": "https://mops.twse.com.tw/mops/#/web/t05sr01_1",
      "is_revenue": false,
      "source": "mops"
    },
    {
      "title": "【4772 台特化】代重要子公司弘潔科技股份有限公司公告\r\n董事會決議召開115年股東常會相關事宜(新增議案)",
      "summary": "",
      "published": "04/13 16:03",
      "link": "https://mops.twse.com.tw/mops/#/web/t05sr01_1",
      "is_revenue": false,
      "source": "mops"
    },
    {
      "title": "【4772 台特化】代重要子公司弘潔科技股份有限公司公告董事會決議股利分派",
      "summary": "",
      "published": "04/13 16:03",
      "link": "https://mops.twse.com.tw/mops/#/web/t05sr01_1",
      "is_revenue": false,
      "source": "mops"
    },
    {
      "title": "【4772 台特化】代重要子公司弘潔科技股份有限公司公告董事會決議\r\n辦理盈餘轉增資發行新股案",
      "summary": "",
      "published": "04/13 16:02",
      "link": "https://mops.twse.com.tw/mops/#/web/t05sr01_1",
      "is_revenue": false,
      "source": "mops"
    },
    {
      "title": "【1103 嘉泥】(更正)本公司董事會決議召開115年股東常會議程調整",
      "summary": "",
      "published": "04/13 15:57",
      "link": "https://mops.twse.com.tw/mops/#/web/t05sr01_1",
      "is_revenue": false,
      "source": "mops"
    },
    {
      "title": "【8155 博智】本公司114年第4季關係人交易自結數與會計師查核數差異說明",
      "summary": "",
      "published": "04/13 15:47",
      "link": "https://mops.twse.com.tw/mops/#/web/t05sr01_1",
      "is_revenue": true,
      "source": "mops"
    },
    {
      "title": "【5443 均豪】公告本公司115年第1季自結合併損益",
      "summary": "",
      "published": "04/13 15:44",
      "link": "https://mops.twse.com.tw/mops/#/web/t05sr01_1",
      "is_revenue": true,
      "source": "mops"
    },
    {
      "title": "【5438 東友】公告本公司董事會決議召開115年股東常會相關事宜\n(新增召集事由)",
      "summary": "",
      "published": "04/13 15:42",
      "link": "https://mops.twse.com.tw/mops/#/web/t05sr01_1",
      "is_revenue": false,
      "source": "mops"
    },
    {
      "title": "【2467 志聖】本公司受邀參加寬量國際主辦之「19th Taiwan CEO Week」，會中就本公司115年第1季之財務報告相關資訊暨營運概況進行說明。",
      "summary": "",
      "published": "04/13 15:38",
      "link": "https://mops.twse.com.tw/mops/#/web/t05sr01_1",
      "is_revenue": false,
      "source": "mops"
    },
    {
      "title": "【6863 永道-KY】代子公司永道射頻技術股份有限公司公告2026年度\r\n股東常會之重要決議",
      "summary": "",
      "published": "04/13 15:36",
      "link": "https://mops.twse.com.tw/mops/#/web/t05sr01_1",
      "is_revenue": false,
      "source": "mops"
    },
    {
      "title": "【2467 志聖】公告本公司115年Q1累計合併稅後自結損益",
      "summary": "",
      "published": "04/13 15:33",
      "link": "https://mops.twse.com.tw/mops/#/web/t05sr01_1",
      "is_revenue": true,
      "source": "mops"
    },
    {
      "title": "【6640 均華】公告本公司115年第1季自結合併損益",
      "summary": "",
      "published": "04/13 15:31",
      "link": "https://mops.twse.com.tw/mops/#/web/t05sr01_1",
      "is_revenue": true,
      "source": "mops"
    },
    {
      "title": "【1909 榮成】代重要子公司榮成環科公告一一五年度股東常會重要決議事項",
      "summary": "",
      "published": "04/13 15:30",
      "link": "https://mops.twse.com.tw/mops/#/web/t05sr01_1",
      "is_revenue": false,
      "source": "mops"
    },
    {
      "title": "【6838 台新藥】(調整召集事由)\n公告本公司董事會決議召開115年股東常會相關事宜",
      "summary": "",
      "published": "04/13 15:11",
      "link": "https://mops.twse.com.tw/mops/#/web/t05sr01_1",
      "is_revenue": false,
      "source": "mops"
    },
    {
      "title": "【2236 百達-KY】代重要子公司 PATEC PTE. LTD. 公告發放股利決議",
      "summary": "",
      "published": "04/13 15:10",
      "link": "https://mops.twse.com.tw/mops/#/web/t05sr01_1",
      "is_revenue": false,
      "source": "mops"
    },
    {
      "title": "【3628 盈正】公告本公司董事會決議召開民國115年股東常會\n(補充115/3/11公告)",
      "summary": "",
      "published": "04/13 15:02",
      "link": "https://mops.twse.com.tw/mops/#/web/t05sr01_1",
      "is_revenue": false,
      "source": "mops"
    },
    {
      "title": "【3572 宏芯科技】更正本公司董事會決議召開115年股東常會事宜",
      "summary": "",
      "published": "04/13 14:59",
      "link": "https://mops.twse.com.tw/mops/#/web/t05sr01_1",
      "is_revenue": false,
      "source": "mops"
    },
    {
      "title": "【3572 宏芯科技】公告本公司董事會決議盈餘轉增資發行新股",
      "summary": "",
      "published": "04/13 14:59",
      "link": "https://mops.twse.com.tw/mops/#/web/t05sr01_1",
      "is_revenue": false,
      "source": "mops"
    },
    {
      "title": "【2409 友達】本公司董事會決議召開115年股東常會 \n(召開方式：視訊輔助股東會)(新增討論事項)",
      "summary": "",
      "published": "04/13 14:44",
      "link": "https://mops.twse.com.tw/mops/#/web/t05sr01_1",
      "is_revenue": false,
      "source": "mops"
    },
    {
      "title": "【1589 永冠-KY】永冠-KY董事會決議召開2026年股東常會公告",
      "summary": "",
      "published": "04/13 14:38",
      "link": "https://mops.twse.com.tw/mops/#/web/t05sr01_1",
      "is_revenue": false,
      "source": "mops"
    },
    {
      "title": "【6204 艾華】代重要孫公司東莞艾華電子有限公司公告董事會決議\r\n發放股利",
      "summary": "",
      "published": "04/13 14:33",
      "link": "https://mops.twse.com.tw/mops/#/web/t05sr01_1",
      "is_revenue": false,
      "source": "mops"
    },
    {
      "title": "【8358 金居】董事會決議股利分派",
      "summary": "",
      "published": "04/13 14:26",
      "link": "https://mops.twse.com.tw/mops/#/web/t05sr01_1",
      "is_revenue": false,
      "source": "mops"
    },
    {
      "title": "【3512 皇龍】公告本公司董事會決議召開一一五年股東常會(新增討論議案)",
      "summary": "",
      "published": "04/13 14:23",
      "link": "https://mops.twse.com.tw/mops/#/web/t05sr01_1",
      "is_revenue": false,
      "source": "mops"
    },
    {
      "title": "漲價在即仍遭出清！三大法人倒貨「2檔晶圓代工」4.8萬張　狠砍聯電提款19.2億元",
      "summary": "[FTNN新聞網]記者陳献朋／綜合報導台股加權指數今（13）日收在35457.29點，漲39.46點或0.11%，成交量達7802億元。根據證交所資料，三大法人賣超50.05億元，觀...",
      "published": "04/13 13:30",
      "link": "https://tw.stock.yahoo.com/news/%E6%BC%B2%E5%83%B9%E5%9C%A8%E5%8D%B3%E4%BB%8D%E9%81%AD%E5%87%BA%E6%B8%85-%E4%B8%89%E5%A4%A7%E6%B3%95%E4%BA%BA%E5%80%92%E8%B2%A8-2%E6%AA%94%E6%99%B6%E5%9C%93%E4%BB%A3%E5%B7%A5-4-8%E8%90%AC%E5%BC%B5-133000394.html",
      "is_revenue": false,
      "source": "yahoo"
    },
    {
      "title": "【8358 金居】公告本公司董事會決議召開115年股東常會相關事宜(更正議案)",
      "summary": "",
      "published": "04/13 13:19",
      "link": "https://mops.twse.com.tw/mops/#/web/t05sr01_1",
      "is_revenue": false,
      "source": "mops"
    },
    {
      "title": "轉讓聯合再生　國發基金： 綠能是重點產業",
      "summary": "[NOWNEWS今日新聞] 國發基金投資「綠能國家隊」聯合再生（3576）曾引發不少爭議。國發基金啟動投資退場機制，申報將以一般交易方式出售聯合再生持股，共計420萬1,476股，轉讓期間自...",
      "published": "04/13 13:17",
      "link": "https://tw.news.yahoo.com/%E8%BD%89%E8%AE%93%E8%81%AF%E5%90%88%E5%86%8D%E7%94%9F-%E5%9C%8B%E7%99%BC%E5%9F%BA%E9%87%91-%E7%B6%A0%E8%83%BD%E6%98%AF%E9%87%8D%E9%BB%9E%E7%94%A2%E6%A5%AD-131711279.html",
      "is_revenue": false,
      "source": "yahoo"
    },
    {
      "title": "3月大賺2.24億「年增1338％」！半導體設備廠搶攻台積電供應鏈發酵　股價刷新高",
      "summary": "[FTNN新聞網]記者邱梓欣／綜合報導PCB及半導體設備廠志聖（2467），因達公布注意交易資訊標準，今（13）日公布相關財務業務訊息，3月自結稅後純益2.24億元，...",
      "published": "04/13 13:15",
      "link": "https://tw.stock.yahoo.com/news/3%E6%9C%88%E5%A4%A7%E8%B3%BA2-24%E5%84%84-%E5%B9%B4%E5%A2%9E1338-%E5%8D%8A%E5%B0%8E%E9%AB%94%E8%A8%AD%E5%82%99%E5%BB%A0%E6%90%B6%E6%94%BB%E5%8F%B0%E7%A9%8D%E9%9B%BB%E4%BE%9B%E6%87%89%E9%8F%88%E7%99%BC%E9%85%B5-%E8%82%A1%E5%83%B9%E5%88%B7%E6%96%B0%E9%AB%98-131500843.html",
      "is_revenue": false,
      "source": "yahoo"
    },
    {
      "title": "讓全球買主體驗台南美味  「台南隊」下周前進新加坡食品展",
      "summary": "[Newtalk新聞] 亞洲年度貿易盛事「2026新加坡國際食品展（FHA2026）」即將在4/21-4/24新加坡博覽中心盛大登場，台南市政府今年再次集結在地優質農業廠商組成「台南隊」，準備以最高規格開拓東南亞市場。今(13)日舉辦展前記者會，副市長葉澤山代表市長黃偉哲宣布，當季鮮甜鳳梨已準備就緒，正式啟航。 黃偉哲對此表示，台南農產具極高國際競爭力，本次由9家指標性業者領軍，期盼讓新加坡及全球買主親自體驗台南在地美味，助益訂單豐碩再創佳績。新加坡是亞洲重要的食品貿易樞紐，更是台南農產品外銷東南亞的核心平台，今年台南隊在東京及英國食品展接連創下亮眼佳績，成功打響國際名聲，接下來的新加坡食品展",
      "published": "04/13 13:03",
      "link": "https://tw.news.yahoo.com/%E8%AE%93%E5%85%A8%E7%90%83%E8%B2%B7%E4%B8%BB%E9%AB%94%E9%A9%97%E5%8F%B0%E5%8D%97%E7%BE%8E%E5%91%B3-%E5%8F%B0%E5%8D%97%E9%9A%8A-%E4%B8%8B%E5%91%A8%E5%89%8D%E9%80%B2%E6%96%B0%E5%8A%A0%E5%9D%A1%E9%A3%9F%E5%93%81%E5%B1%95-130355299.html",
      "is_revenue": false,
      "source": "yahoo"
    },
    {
      "title": "是隔日衝還是真題材？三大法人賣超50億卻猛掃「台塑集團2檔」　外資、自營商都搶瘋了",
      "summary": "[FTNN新聞網]記者何亞軒／綜合報導台股加權指數今（13）日收盤35,457.29點，漲39.46點，漲幅0.11%，三大法人合計賣超50.05億元，觀察今日三大法人買超個股，...",
      "published": "04/13 13:00",
      "link": "https://tw.stock.yahoo.com/news/%E6%98%AF%E9%9A%94%E6%97%A5%E8%A1%9D%E9%82%84%E6%98%AF%E7%9C%9F%E9%A1%8C%E6%9D%90-%E4%B8%89%E5%A4%A7%E6%B3%95%E4%BA%BA%E8%B3%A3%E8%B6%8550%E5%84%84%E5%8D%BB%E7%8C%9B%E6%8E%83-%E5%8F%B0%E5%A1%91%E9%9B%86%E5%9C%982%E6%AA%94-%E5%A4%96%E8%B3%87-%E8%87%AA%E7%87%9F%E5%95%86%E9%83%BD%E6%90%B6%E7%98%8B%E4%BA%86-130000135.html",
      "is_revenue": false,
      "source": "yahoo"
    },
    {
      "title": "PCB一片紅！「這3檔」亮第2顆紅燈牽泰鼎、邑昇漲停　高技、鉅橡達連5漲逾30%",
      "summary": "[FTNN新聞網]記者陳献朋／綜合報導由於美伊在長達21小時的談判中依舊無法取得對停戰條件的共識，台股大盤今（13）日僅小漲39.46點或0.11%，加權指數落在35457...",
      "published": "04/13 12:45",
      "link": "https://tw.stock.yahoo.com/news/pcb-%E7%89%87%E7%B4%85-%E9%80%993%E6%AA%94-%E4%BA%AE%E7%AC%AC2%E9%A1%86%E7%B4%85%E7%87%88%E7%89%BD%E6%B3%B0%E9%BC%8E-%E9%82%91%E6%98%87%E6%BC%B2%E5%81%9C-124500775.html",
      "is_revenue": false,
      "source": "yahoo"
    },
    {
      "title": "快訊／撤出聯合再生？　國發會聲明全文",
      "summary": "一、國發基金的設置旨在支持國家策略性產業發展，綠能產業為現階段國家重點產業，本案屬國發基金投資事業之例行性退場作業，不涉及產業扶植目標的移轉。",
      "published": "04/13 12:44",
      "link": "https://tw.news.yahoo.com/%E5%BF%AB%E8%A8%8A-%E6%92%A4%E5%87%BA%E8%81%AF%E5%90%88%E5%86%8D%E7%94%9F-%E5%9C%8B%E7%99%BC%E6%9C%83%E8%81%B2%E6%98%8E%E5%85%A8%E6%96%87-124400918.html",
      "is_revenue": false,
      "source": "yahoo"
    },
    {
      "title": "元大金3月大賺46億　單累獲利均刷同期新高",
      "summary": "元大金控今（13）日公布獲利自結數，銀行、投信與期貨等3家子公司3月賺出歷年同期新高推升下，元大金3月稅後純益46.16億元、年增83.0%，單月獲利金額為歷年同期新高。累計數方面，元大金前3月稅後純益144.09億元、年增88.6%，反映證券、銀行、投信、期貨等4家子公司前3月獲利創歷年同期新高，推升母金控累積獲利亦創同期新高。元大金前3月每股稅後純益（E......",
      "published": "04/13 12:30",
      "link": "https://tw.news.yahoo.com/%E5%85%83%E5%A4%A7%E9%87%913%E6%9C%88%E5%A4%A7%E8%B3%BA46%E5%84%84-%E5%96%AE%E7%B4%AF%E7%8D%B2%E5%88%A9%E5%9D%87%E5%88%B7%E5%90%8C%E6%9C%9F%E6%96%B0%E9%AB%98-123007397.html",
      "is_revenue": false,
      "source": "yahoo"
    },
    {
      "title": "Q1營收亮眼寫新高！「晶圓大廠」難逃外資放量狂瀉5萬張　提款30億、慘崩3%",
      "summary": "[FTNN新聞網]記者邱梓欣／綜合報導受美伊談判破局影響，台股今（13）日以35422.91點開高後一度下跌156.1點，但盤中跌幅收斂，終場加權指數翻紅收在35457.29點...",
      "published": "04/13 12:30",
      "link": "https://tw.stock.yahoo.com/news/q1%E7%87%9F%E6%94%B6%E4%BA%AE%E7%9C%BC%E5%AF%AB%E6%96%B0%E9%AB%98-%E6%99%B6%E5%9C%93%E5%A4%A7%E5%BB%A0-%E9%9B%A3%E9%80%83%E5%A4%96%E8%B3%87%E6%94%BE%E9%87%8F%E7%8B%82%E7%80%895%E8%90%AC%E5%BC%B5-%E6%8F%90%E6%AC%BE30%E5%84%84-%E6%85%98%E5%B4%A93-123000752.html",
      "is_revenue": true,
      "source": "yahoo"
    },
    {
      "title": "國發基金：申讓聯合再生為例行退場　綠能仍為重點產業",
      "summary": "（中央社記者潘姿羽台北13日電）國發基金啟動退場機制，申讓聯合再生持股，衝擊聯合再生今天股價跌停。國發基金晚間做出3點說明，強調策略投資階段性目的達成，因而進行例行性退場作業，不涉及產業扶植目標移轉，綠能產業仍是現階段國家重點產業。",
      "published": "04/13 12:29",
      "link": "https://tw.news.yahoo.com/%E5%9C%8B%E7%99%BC%E5%9F%BA%E9%87%91-%E7%94%B3%E8%AE%93%E8%81%AF%E5%90%88%E5%86%8D%E7%94%9F%E7%82%BA%E4%BE%8B%E8%A1%8C%E9%80%80%E5%A0%B4-%E7%B6%A0%E8%83%BD%E4%BB%8D%E7%82%BA%E9%87%8D%E9%BB%9E%E7%94%A2%E6%A5%AD-122902681.html",
      "is_revenue": false,
      "source": "yahoo"
    },
    {
      "title": "轉讓「聯合再生」持股致股價重挫　國發基金：階段性目的已達成",
      "summary": "國發基金啟動申報轉讓聯合再生能源持股，引發市場信心動搖，聯合再生今（4/13）開盤即跌停鎖死至17.1元至收盤，賣壓沉重。國發基金今晚表示，考量國發基金策略投資階段性目的已達成，爰依既定投資事業退場機制檢視並適時辦理聯合再生釋股，以回收資金持續投入國內產業發展。",
      "published": "04/13 12:26",
      "link": "https://tw.news.yahoo.com/%E8%BD%89%E8%AE%93-%E8%81%AF%E5%90%88%E5%86%8D%E7%94%9F-%E6%8C%81%E8%82%A1%E8%87%B4%E8%82%A1%E5%83%B9%E9%87%8D%E6%8C%AB-%E5%9C%8B%E7%99%BC%E5%9F%BA%E9%87%91-%E9%9A%8E%E6%AE%B5%E6%80%A7%E7%9B%AE%E7%9A%84%E5%B7%B2%E9%81%94%E6%88%90-122627844.html",
      "is_revenue": false,
      "source": "yahoo"
    },
    {
      "title": "台積電擴產點火！「半導體設備廠」炸連5漲52.3%寫新天價　弘塑、均華、意得士漲停創高",
      "summary": "[FTNN新聞網]記者陳献朋／綜合報導雖然美伊最新談判並沒有將戰爭進一步推向結束，但台股大盤今（13）日仍成功收紅，加權指數終場收在35457.29點，寫出歷史新...",
      "published": "04/13 12:15",
      "link": "https://tw.stock.yahoo.com/news/%E5%8F%B0%E7%A9%8D%E9%9B%BB%E6%93%B4%E7%94%A2%E9%BB%9E%E7%81%AB-%E5%8D%8A%E5%B0%8E%E9%AB%94%E8%A8%AD%E5%82%99%E5%BB%A0-%E7%82%B8%E9%80%A35%E6%BC%B252-3-%E5%AF%AB%E6%96%B0%E5%A4%A9%E5%83%B9-121500947.html",
      "is_revenue": false,
      "source": "yahoo"
    },
    {
      "title": "【5534 長虹】代子公司(虹欣建設)公告其一一五年股東常會重要\r\n決議事項。",
      "summary": "",
      "published": "04/13 10:52",
      "link": "https://mops.twse.com.tw/mops/#/web/t05sr01_1",
      "is_revenue": false,
      "source": "mops"
    },
    {
      "title": "【2718 全心投控】修正公告本公司董事會決議114年第四季分派股利(董事會決議日為115/04/10，誤植為114/04/10，故作更正)",
      "summary": "",
      "published": "04/13 10:21",
      "link": "https://mops.twse.com.tw/mops/#/web/t05sr01_1",
      "is_revenue": false,
      "source": "mops"
    },
    {
      "title": "【1773 勝一】公告115年第一季財務報告董事會召開日期",
      "summary": "",
      "published": "04/13 10:17",
      "link": "https://mops.twse.com.tw/mops/#/web/t05sr01_1",
      "is_revenue": false,
      "source": "mops"
    },
    {
      "title": "【1210 大成】公告本公司於115年04月14日召開法說會相關內容",
      "summary": "",
      "published": "04/13 09:28",
      "link": "https://mops.twse.com.tw/mops/#/web/t05sr01_1",
      "is_revenue": false,
      "source": "mops"
    },
    {
      "title": "【8083 瑞穎】115年第1季\r\n財務報告董事會預計召開日期為115年04月23日。",
      "summary": "",
      "published": "04/13 09:00",
      "link": "https://mops.twse.com.tw/mops/#/web/t05sr01_1",
      "is_revenue": false,
      "source": "mops"
    }
  ]
}