{
  "fetched_at": "2026-04-14T14:18:51.990236",
  "items": [
    {
      "title": "【6588 東典光電】本公司有價證券近期達公佈注意交易資訊標準， 故公告相關訊息，以利投資人區別暸解",
      "summary": "",
      "published": "04/14 14:11",
      "link": "https://mops.twse.com.tw/mops/#/web/t05sr01_1",
      "is_revenue": false,
      "source": "mops"
    },
    {
      "title": "【6218 豪勉】本公司有價證券近期多次達公布注意交易資訊標準， 故公告相關訊息，以利投資人區別暸解。",
      "summary": "",
      "published": "04/14 14:05",
      "link": "https://mops.twse.com.tw/mops/#/web/t05sr01_1",
      "is_revenue": false,
      "source": "mops"
    },
    {
      "title": "【4542 科嶠】本公司有價證券近期多次達公布注意交易資訊標準，故公告 相關訊息，以利投資人區別暸解。",
      "summary": "",
      "published": "04/14 14:04",
      "link": "https://mops.twse.com.tw/mops/#/web/t05sr01_1",
      "is_revenue": false,
      "source": "mops"
    },
    {
      "title": "【2892 第一金】公告本公司暨主要子公司115年3月份自結合併盈餘數",
      "summary": "",
      "published": "04/14 13:56",
      "link": "https://mops.twse.com.tw/mops/#/web/t05sr01_1",
      "is_revenue": true,
      "source": "mops"
    },
    {
      "title": "【6147 頎邦】本公司有價證券近期達公布注意交易資訊標準， 故公告相關訊息，以利投資人區別暸解",
      "summary": "",
      "published": "04/14 13:52",
      "link": "https://mops.twse.com.tw/mops/#/web/t05sr01_1",
      "is_revenue": false,
      "source": "mops"
    },
    {
      "title": "恆大欺詐案深圳開審  許家印當庭認罪擇期宣判",
      "summary": "（中央社台北14日電）新華社報道，恆大集團涉及非法吸收公眾存款、集資詐騙、欺詐發行證券等案件13日至14日在深圳開審，被告恆大集團創辦人許家印當庭表示認罪悔罪，法庭將擇期宣判。",
      "published": "04/14 05:59",
      "link": "https://tw.news.yahoo.com/%E6%81%86%E5%A4%A7%E6%AC%BA%E8%A9%90%E6%A1%88%E6%B7%B1%E5%9C%B3%E9%96%8B%E5%AF%A9-%E8%A8%B1%E5%AE%B6%E5%8D%B0%E7%95%B6%E5%BA%AD%E8%AA%8D%E7%BD%AA%E6%93%87%E6%9C%9F%E5%AE%A3%E5%88%A4-055901825.html",
      "is_revenue": false,
      "source": "yahoo"
    },
    {
      "title": "收盤／台股吃無敵星星　衝破3萬6！雙頭馬車觸新天價　台積電狂飆2055元",
      "summary": "台股今天真的是殺紅了眼，大盤指數像吃了無敵星星一樣一路往上衝，直接噴破三萬六千點大關，收盤爆出歷史新天價，來到36296.12點！滿盤的紅字讓全台灣股民今天看盤看到嘴角都下不來。面對這種百年難得一見的超級大多頭行情，你如果還在場外觀望，真的是會搥心肝！",
      "published": "04/14 05:59",
      "link": "https://tw.news.yahoo.com/%E6%94%B6%E7%9B%A4-%E5%8F%B0%E8%82%A1%E5%90%83%E7%84%A1%E6%95%B5%E6%98%9F%E6%98%9F-%E8%A1%9D%E7%A0%B43%E8%90%AC6-%E9%9B%99%E9%A0%AD%E9%A6%AC%E8%BB%8A%E8%A7%B8%E6%96%B0%E5%A4%A9%E5%83%B9-%E5%8F%B0%E7%A9%8D%E9%9B%BB%E7%8B%82%E9%A3%862055%E5%85%83-055900642.html",
      "is_revenue": false,
      "source": "yahoo"
    },
    {
      "title": "東元搶進農用及商用無人機市場，推新世代電巴扁線油冷高功率動力系統",
      "summary": "【財訊快報／記者戴海茜報導】2026台北國際汽車零配件展（TAIPEI AMPA）今日開展，東元(1504)以電動載具動力系統解決方案為主軸參展，首度發表「T Power Pro 400kW扁線油冷直驅馬達」，並同步展出高酬載商用無人機動力系統，有效載荷能力可以達到150公斤，拓展電動巴士及商、農用無人機市場。東元總經理高飛鳶表示，隨著全球交通運輸邁向電動化，市場對動力系統的要求已不再局限於單一性能表現，看重整體解決方案的能力，東元協助客戶加速布局電動載具市場，搶新一波成長商機。東元在台首度發表「T Power Pro 400kW扁線油冷直驅馬達」，有助於電動巴士業者加速車型迭代升級，強化整體",
      "published": "04/14 05:58",
      "link": "https://tw.stock.yahoo.com/news/%E6%9D%B1%E5%85%83%E6%90%B6%E9%80%B2%E8%BE%B2%E7%94%A8%E5%8F%8A%E5%95%86%E7%94%A8%E7%84%A1%E4%BA%BA%E6%A9%9F%E5%B8%82%E5%A0%B4-%E6%8E%A8%E6%96%B0%E4%B8%96%E4%BB%A3%E9%9B%BB%E5%B7%B4%E6%89%81%E7%B7%9A%E6%B2%B9%E5%86%B7%E9%AB%98%E5%8A%9F%E7%8E%87%E5%8B%95%E5%8A%9B%E7%B3%BB%E7%B5%B1-055826319.html",
      "is_revenue": false,
      "source": "yahoo"
    },
    {
      "title": "建通亮相台北國際汽機車零配件展，看好今年營運步入高成長",
      "summary": "【財訊快報／記者陳浩寧報導】建通(2460)登陸「2026 TAIPEI AMPA（台北國際汽機車零配件展）」及「E-Mobility Taiwan（台灣國際智慧移動展）」，系統化展示旗下特殊新型銅材、國標新絕緣插頭端子、車用線束端子等利基製品，凸顯在車用新能源、高品質電力工程、AI散熱及端子領域的最新研發成果，從精密端子大廠擴增為高階材料供應商。建通指出，本次參展核心圍繞「能源創新、國標轉換、跨域整合」三大主題，隨著3月營收衝上4.57億元歷史新高，台灣特殊新型銅材廠的產能與良率已進入成熟期。建通將於現場展示高純度銅材與異型導體銅材，專為電力傳輸系統設計匯流銅排，大幅提升導電效率；符合新能源",
      "published": "04/14 05:55",
      "link": "https://tw.stock.yahoo.com/news/%E5%BB%BA%E9%80%9A%E4%BA%AE%E7%9B%B8%E5%8F%B0%E5%8C%97%E5%9C%8B%E9%9A%9B%E6%B1%BD%E6%A9%9F%E8%BB%8A%E9%9B%B6%E9%85%8D%E4%BB%B6%E5%B1%95-%E7%9C%8B%E5%A5%BD%E4%BB%8A%E5%B9%B4%E7%87%9F%E9%81%8B%E6%AD%A5%E5%85%A5%E9%AB%98%E6%88%90%E9%95%B7-055546459.html",
      "is_revenue": false,
      "source": "yahoo"
    },
    {
      "title": "台積電、AI供應鏈、大立光、台塑集團齊步走，台股創歷史新高",
      "summary": "【財訊快報／方亞申】美國總統川普週一盤中表示，伊朗方面有合適的人致電美方，表示希望達成協議，美伊二次會談似乎有譜。在此之前，美國宣布對所有進出伊朗港口的海上交通實施全面封鎖。國際油價因為川普一句話而拉回但股市反彈，費半指數持續創歷史新高，標普及那指站上季線向高點推升，道瓊來到季線附近。亞洲股市則是日韓泰都大漲1.5-3.5%，台股週二直接開高震盪，銅箔基板三雄表現強勢創高，AI供應鏈包括散熱、滑軌、交換器、機殼以及記憶體等，一直到下游組裝的廣達(2382)、鴻海(2317)表現都很好；再加上矽智財創意(3443)等族群，以及高價股信驊(5274)、穎崴(6515)、大立光(3008)。傳產台塑",
      "published": "04/14 05:50",
      "link": "https://tw.stock.yahoo.com/news/%E5%8F%B0%E7%A9%8D%E9%9B%BB-ai%E4%BE%9B%E6%87%89%E9%8F%88-%E5%A4%A7%E7%AB%8B%E5%85%89-%E5%8F%B0%E5%A1%91%E9%9B%86%E5%9C%98%E9%BD%8A%E6%AD%A5%E8%B5%B0-%E5%8F%B0%E8%82%A1%E5%89%B5%E6%AD%B7%E5%8F%B2%E6%96%B0%E9%AB%98-055004412.html",
      "is_revenue": false,
      "source": "yahoo"
    },
    {
      "title": "台股價量齊揚！終場收36296點、大漲838點　台積電收2055元新天價",
      "summary": "即時中心／綜合報導儘管美伊局勢持續緊張，但川普稱伊朗來電盼能達成協議，投資人認為中東戰爭仍有望解決，美股主要指數週一（13日）開低走高。台股今（14）日以35,584.09點開出、漲126.8點，隨後迅速衝擊歷史新高，突破3萬6大關；盤中持續走高，終場指數就以36,296.12點作收、大漲838.83點，漲幅2.37％，成交量9,717.31億元。台積電（2330）終場以新天價2,055元作收、上漲65元。",
      "published": "04/14 05:49",
      "link": "https://tw.stock.yahoo.com/news/%E5%8F%B0%E8%82%A1%E5%83%B9%E9%87%8F%E9%BD%8A%E6%8F%9A-%E7%B5%82%E5%A0%B4%E6%94%B636296%E9%BB%9E-%E5%A4%A7%E6%BC%B2838%E9%BB%9E-%E5%8F%B0%E7%A9%8D%E9%9B%BB%E6%94%B62055%E5%85%83%E6%96%B0%E5%A4%A9%E5%83%B9-054921936.html",
      "is_revenue": false,
      "source": "yahoo"
    },
    {
      "title": "台積電暴衝收2055元新天價！ 指數大漲838點收36296創新高",
      "summary": "受惠美伊談判超乎期待，投資人對後續和平對話走向樂觀，台股今（14）天盤中展現強悍多頭氣勢，衝上3萬6千點關卡，最高彈至36341.44點，最終漲838.83點，收在36296.12點，盤中收盤指數雙創",
      "published": "04/14 05:47",
      "link": "https://tw.news.yahoo.com/%E5%8F%B0%E7%A9%8D%E9%9B%BB%E6%9A%B4%E8%A1%9D%E6%94%B62055%E5%85%83%E6%96%B0%E5%A4%A9%E5%83%B9-%E6%8C%87%E6%95%B8%E5%A4%A7%E6%BC%B2838%E9%BB%9E%E6%94%B636296%E5%89%B5%E6%96%B0%E9%AB%98-054754181.html",
      "is_revenue": false,
      "source": "yahoo"
    },
    {
      "title": "台積電終場收2055元！台股終場上漲838點",
      "summary": "[NOWNEWS今日新聞]市場情緒仍轉趨樂觀，對美伊有望達成協議的預期升溫下，美國股市週一全數走高，帶動台北股市今（14）日開盤上漲126.8點、來到35584.09點，在權王台積電創新高的帶動下，指...",
      "published": "04/14 05:44",
      "link": "https://tw.news.yahoo.com/%E5%8F%B0%E7%A9%8D%E9%9B%BB%E7%B5%82%E5%A0%B4%E6%94%B62055%E5%85%83-%E5%8F%B0%E8%82%A1%E7%B5%82%E5%A0%B4%E4%B8%8A%E6%BC%B2838%E9%BB%9E-054453440.html",
      "is_revenue": false,
      "source": "yahoo"
    },
    {
      "title": "台積電、信驊創天價　台股漲838點收36296點創新高",
      "summary": "（中央社記者張建中台北14日電）台股今天開高走高，加權指數盤中最高達36341.44點，創下歷史新高，終場漲勢收斂，收在36296.12點，上漲838.83點，收盤指數創下新高，成交值新台幣9717.31億元。",
      "published": "04/14 05:42",
      "link": "https://tw.news.yahoo.com/%E5%8F%B0%E7%A9%8D%E9%9B%BB-%E4%BF%A1%E9%A9%8A%E5%89%B5%E5%A4%A9%E5%83%B9-%E5%8F%B0%E8%82%A1%E6%BC%B2838%E9%BB%9E%E6%94%B636296%E9%BB%9E%E5%89%B5%E6%96%B0%E9%AB%98-054239221.html",
      "is_revenue": false,
      "source": "yahoo"
    },
    {
      "title": "台積電大噴發！飆2055元新天價 台股收盤漲838點創新高",
      "summary": "台股今（14）日氣勢如虹再度創新高，指數一度狂漲近900點，最高來到36341.44點，終場上漲838.83點收36296.12點。",
      "published": "04/14 05:41",
      "link": "https://tw.stock.yahoo.com/news/%E5%8F%B0%E7%A9%8D%E9%9B%BB%E5%A4%A7%E5%99%B4%E7%99%BC-%E9%A3%862055%E5%85%83%E6%96%B0%E5%A4%A9%E5%83%B9-%E5%8F%B0%E8%82%A1%E6%94%B6%E7%9B%A4%E6%BC%B2838%E9%BB%9E%E5%89%B5%E6%96%B0%E9%AB%98-054127910.html",
      "is_revenue": false,
      "source": "yahoo"
    },
    {
      "title": "只領到「台積電配息1元」！股民看「投資細節」笑了",
      "summary": "財經中心／李明融報導「護國神山」台積電（2330）是許多投資人的首選，除了看好股價未來成長趨勢，每年的配息也是關注焦點。台積電日前宣布配發每股6元現金股利，總發放規模高達1556億元，超過200萬名股東受惠。然而，有股民發文表示自己竟只收到「1元配息」，了解真相後讓網友不禁直呼：「銀行賺得比你多！」。",
      "published": "04/14 05:37",
      "link": "https://tw.stock.yahoo.com/news/%E5%8F%AA%E9%A0%98%E5%88%B0-%E5%8F%B0%E7%A9%8D%E9%9B%BB%E9%85%8D%E6%81%AF1%E5%85%83-%E8%82%A1%E6%B0%91%E7%9C%8B-%E6%8A%95%E8%B3%87%E7%B4%B0%E7%AF%80-%E7%AC%91%E4%BA%86-053743770.html",
      "is_revenue": false,
      "source": "yahoo"
    },
    {
      "title": "雙王法說台積電攻新天價大立光亮燈！ 台股暴漲838點輕取三萬六",
      "summary": "川普釋出伊朗盼達成協議，美股延續上行，科技股帶動那指領漲，半導體族群維持強勢，顯示資金持續集中AI主軸。台指期夜盤大漲567點，台積電法說會前續揚，重返2000元大關，收盤創下2055元天價，同天法說的大立光在CPO題材帶動下，亮燈漲停。台股先噴838點，攻上36296點，輕取三萬六天險。",
      "published": "04/14 05:36",
      "link": "https://tw.news.yahoo.com/%E5%8F%B0%E8%82%A1%E6%9A%B4%E6%BC%B26%E7%99%BE%E9%BB%9E%E6%94%BB%E5%85%8B%E4%B8%89%E8%90%AC%E5%85%AD%E5%A4%A9%E9%9A%AA-%E5%8F%B0%E7%A9%8D%E9%9B%BB%E9%87%8D%E8%BF%942%E5%8D%83%E5%85%83%E5%A4%A7%E9%97%9C%E5%86%8D%E5%B9%B32025%E5%A4%A9%E5%83%B9-010600802.html",
      "is_revenue": false,
      "source": "yahoo"
    },
    {
      "title": "宏泰人壽疑捲非常規交易案　檢調今低調搜索偵訊中",
      "summary": "宏泰集團旗下宏泰人壽今天（14日）驚傳遭檢調搜索。據了解，檢調此次行動鎖定一起非常規交易案，上午已前往公司調閱相關資料，並同步約談多名疑涉案人士。儘管辦案人員行動低調、未",
      "published": "04/14 05:33",
      "link": "https://tw.news.yahoo.com/%E5%AE%8F%E6%B3%B0%E4%BA%BA%E5%A3%BD%E7%96%91%E6%8D%B2%E9%9D%9E%E5%B8%B8%E8%A6%8F%E4%BA%A4%E6%98%93%E6%A1%88-%E6%AA%A2%E8%AA%BF%E4%BB%8A%E4%BD%8E%E8%AA%BF%E6%90%9C%E7%B4%A2%E5%81%B5%E8%A8%8A%E4%B8%AD-053300881.html",
      "is_revenue": false,
      "source": "yahoo"
    }
  ]
}