{
  "fetched_at": "2026-07-11T10:38:18.459977",
  "items": [
    {
      "title": "【iPhone 18漲價潮2】漲價受惠股點點名！專家揭台積電、大立光、鴻海等蘋概股誰最吃香",
      "summary": "市場傳出蘋果iPhone 18系列將因零組件成本增加而調漲售價，引發市場關注漲價效應是否擴散至供應鏈。專家表示，iPhone售價調升對台灣供應鏈來說偏向正面解讀，可提升上游供應商的議價空間，但若要沿著題材布局，仍須聚焦具技術門檻、取代性低的廠商，而非全面看好所有蘋概股，尤其點名晶片相關供應鏈如台積電、京元電、群聯、南亞科、華邦電等記憶體相關廠商。",
      "published": "07/11 02:32",
      "link": "https://tw.stock.yahoo.com/news/%E3%80%90iphone-18%E6%BC%B2%E5%83%B9%E6%BD%AE2%E3%80%91%E6%BC%B2%E5%83%B9%E5%8F%97%E6%83%A0%E8%82%A1%E9%BB%9E%E9%BB%9E%E5%90%8D%EF%BC%81%E5%B0%88%E5%AE%B6%E6%8F%AD%E5%8F%B0%E7%A9%8D%E9%9B%BB%E3%80%81%E5%A4%A7%E7%AB%8B%E5%85%89%E3%80%81%E9%B4%BB%E6%B5%B7%E7%AD%89%E8%98%8B%E6%A6%82%E8%82%A1%E8%AA%B0%E6%9C%80%E5%90%83%E9%A6%99-023258339.html",
      "is_revenue": false,
      "source": "yahoo"
    },
    {
      "title": "巴威颱風影響　新光三越10店遠東SOGO全台11日停業",
      "summary": "（中央社記者江明晏台北11日電）受颱風巴威影響，全台多縣市連兩日停班停課，百貨商場也持續調整營業措施，台北101、新光三越、遠東百貨、遠東SOGO、微風、京站及誠品生活等今天宣布部分或全數據點暫停營業，其中北部、中部百貨多數均停業。",
      "published": "07/11 02:11",
      "link": "https://tw.news.yahoo.com/%E5%B7%B4%E5%A8%81%E9%A2%B1%E9%A2%A8%E5%BD%B1%E9%9F%BF-%E6%96%B0%E5%85%89%E4%B8%89%E8%B6%8A10%E5%BA%97%E9%81%A0%E6%9D%B1sogo%E5%85%A8%E5%8F%B011%E6%97%A5%E5%81%9C%E6%A5%AD-021121799.html",
      "is_revenue": false,
      "source": "yahoo"
    },
    {
      "title": "DRAM一直漲價一直賺！　南亞科Q2毛利率暴衝79.5%",
      "summary": "南亞科第二季營收825.49億元，季增68.2％；營業毛利656.19億元，毛利率79.5％，季增11.6%；營業利益608.26億元，營業利益率73.7％，季增12.4%；稅後純益501.92億元，單季每股稅後純益（EPS）14.66元。累計上半年稅後純益762.5億元，EPS為23.38元。南亞科上半年應用於AI基礎設...",
      "published": "07/11 02:00",
      "link": "https://tw.news.yahoo.com/dram-%E7%9B%B4%E6%BC%B2%E5%83%B9-%E7%9B%B4%E8%B3%BA-%E5%8D%97%E4%BA%9E%E7%A7%91q2%E6%AF%9B%E5%88%A9%E7%8E%87%E6%9A%B4%E8%A1%9D79-5-020046468.html",
      "is_revenue": false,
      "source": "yahoo"
    },
    {
      "title": "王品6月營收20.5億元　創同期新高",
      "summary": "[NOWNEWS今日新聞]王品集團公告6月自結營收，兩岸合併營收新台幣20.5億元，年增16.59%，創同期新高。台灣營收16.5億元，年增14.61%，累計前6月營收為103.7億元，年增9.84%...",
      "published": "07/11 01:56",
      "link": "https://tw.news.yahoo.com/%E7%8E%8B%E5%93%816%E6%9C%88%E7%87%9F%E6%94%B620-5%E5%84%84%E5%85%83-%E5%89%B5%E5%90%8C%E6%9C%9F%E6%96%B0%E9%AB%98-015610188.html",
      "is_revenue": true,
      "source": "yahoo"
    },
    {
      "title": "在手訂單飆上1347億元！「廠務工程大廠」6月、Q2、H1營收同創高　台積電CoWoS、美光HBM擴產加持",
      "summary": "[FTNN新聞網]記者陳献朋／綜合報導廠務工程大廠帆宣（6196）近日公開6月、第二季和上半年營收表現，前兩者創高，後者也為同期最佳，顯示公司接單情形優異，目...",
      "published": "07/11 01:45",
      "link": "https://tw.stock.yahoo.com/news/%E5%9C%A8%E6%89%8B%E8%A8%82%E5%96%AE%E9%A3%86%E4%B8%8A1347%E5%84%84%E5%85%83-%E5%BB%A0%E5%8B%99%E5%B7%A5%E7%A8%8B%E5%A4%A7%E5%BB%A0-6%E6%9C%88-q2-h1%E7%87%9F%E6%94%B6%E5%90%8C%E5%89%B5%E9%AB%98-014500569.html",
      "is_revenue": true,
      "source": "yahoo"
    },
    {
      "title": "SK海力士赴美掛牌狂噴13％！美光遇強敵臉綠了 台積電ADR也收低",
      "summary": "韓國記憶體大廠SK海力士（SK hynix）在美國那斯達克掛牌首日股價大漲逾12%，帶動市場對AI記憶體族群信心升溫，周五（10日），美股四大指數全面收紅。隨著美股第二季財報季即將展開，市場除聚焦科技企業財報外，也持續關注中東局勢發展，以及是否牽動全球金融市場走勢。",
      "published": "07/11 01:32",
      "link": "https://tw.stock.yahoo.com/news/sk%E6%B5%B7%E5%8A%9B%E5%A3%AB%E8%B5%B4%E7%BE%8E%E6%8E%9B%E7%89%8C%E7%8B%82%E5%99%B413-%E7%BE%8E%E5%85%89%E9%81%87%E5%BC%B7%E6%95%B5%E8%87%89%E7%B6%A0%E4%BA%86-%E5%8F%B0%E7%A9%8D%E9%9B%BBadr%E4%B9%9F%E6%94%B6%E4%BD%8E-013236522.html",
      "is_revenue": false,
      "source": "yahoo"
    },
    {
      "title": "南亞科AI新局2》沒做HBM也賺翻？一次看懂記憶體新遊戲",
      "summary": "AI愈熱，賺錢的產品，不一定只有高頻寬記憶體（HBM）。南亞科沒有主攻HBM，第二季毛利率卻衝上79.5％，創下歷史新高，看似反直覺的結果，其實是AI正重新改寫整個DRAM市場的供需與定價邏輯。 過去，記憶體產業漲幅，往往跟著景氣循環起伏；…",
      "published": "07/11 01:01",
      "link": "https://tw.news.yahoo.com/%E5%8D%97%E4%BA%9E%E7%A7%91ai%E6%96%B0%E5%B1%802-%E6%B2%92%E5%81%9Ahbm%E4%B9%9F%E8%B3%BA%E7%BF%BB-%E6%AC%A1%E7%9C%8B%E6%87%82%E8%A8%98%E6%86%B6%E9%AB%94%E6%96%B0%E9%81%8A%E6%88%B2-010100927.html",
      "is_revenue": false,
      "source": "yahoo"
    },
    {
      "title": "標普500逼歷史新高　美股回神、台股ADR多數走低",
      "summary": "受SK海力士進軍美國影響，半導體類股普遍表現疲軟，美光科技（Micron）股價下跌近2%；邁威爾科技與英特爾跌幅超3%；iShares半導體 ETF（SOXX）同步走低約1%。美股主要指數表現，道瓊指數上漲149.60 點、0.29%，收至52637.01點；那斯達克指數上漲74.72點、0.29%，收在26281.61...",
      "published": "07/11 01:00",
      "link": "https://tw.news.yahoo.com/%E6%A8%99%E6%99%AE500%E9%80%BC%E6%AD%B7%E5%8F%B2%E6%96%B0%E9%AB%98-%E7%BE%8E%E8%82%A1%E5%9B%9E%E7%A5%9E-%E5%8F%B0%E8%82%A1adr%E5%A4%9A%E6%95%B8%E8%B5%B0%E4%BD%8E-010040255.html",
      "is_revenue": false,
      "source": "yahoo"
    },
    {
      "title": "中聯癌油》福懋油吳星澄才當董事長3個月出事　劉偉龍接手泰山才3年...",
      "summary": "台中地檢署9日再度指揮警、調及食安單位兵分多路搜索中聯油脂、福壽實業、福懋油脂及",
      "published": "07/11 01:00",
      "link": "https://tw.news.yahoo.com/%E4%B8%AD%E8%81%AF%E7%99%8C%E6%B2%B9-%E7%A6%8F%E6%87%8B%E6%B2%B9%E5%90%B3%E6%98%9F%E6%BE%84%E6%89%8D%E7%95%B6%E8%91%A3%E4%BA%8B%E9%95%B73%E5%80%8B%E6%9C%88%E5%87%BA%E4%BA%8B-%E5%8A%89%E5%81%89%E9%BE%8D%E6%8E%A5%E6%89%8B%E6%B3%B0%E5%B1%B1%E6%89%8D3%E5%B9%B4-010033766.html",
      "is_revenue": false,
      "source": "yahoo"
    },
    {
      "title": "南亞科AI新局1》毛利狠甩台積電　明年先砸2千億押AI下一局",
      "summary": "比起第二季毛利率衝上79.5％、高於台積電第二季財測區間，南亞科決定趁勝追擊，提早投入下一輪AI競賽，總經理李培瑛透露，2027年資本支出將一口氣提高至逾2,000億元，遠高於今年500多億元，並同步推進新廠、先進製程及客製化AI記憶體布局…",
      "published": "07/11 01:00",
      "link": "https://tw.news.yahoo.com/%E5%8D%97%E4%BA%9E%E7%A7%91ai%E6%96%B0%E5%B1%801-%E6%AF%9B%E5%88%A9%E7%8B%A0%E7%94%A9%E5%8F%B0%E7%A9%8D%E9%9B%BB-%E6%98%8E%E5%B9%B4%E5%85%88%E7%A0%B82%E5%8D%83%E5%84%84%E6%8A%BCai%E4%B8%8B-%E5%B1%80-010000620.html",
      "is_revenue": false,
      "source": "yahoo"
    },
    {
      "title": "6月營收創近238個月新高！這「鑽針廠」受惠AI伺服器、高階PCB需求　H1營收年增逾6成",
      "summary": "[FTNN新聞網]記者黃詩雯／綜合報導AI伺服器帶動高階PCB需求持續成長，PCB鑽針廠凱崴（5498）受惠於鑽針需求升溫，6月營收繳出亮眼成績，單月、單季及上半年營...",
      "published": "07/11 01:00",
      "link": "https://tw.stock.yahoo.com/news/6%E6%9C%88%E7%87%9F%E6%94%B6%E5%89%B5%E8%BF%91238%E5%80%8B%E6%9C%88%E6%96%B0%E9%AB%98-%E9%80%99-%E9%91%BD%E9%87%9D%E5%BB%A0-%E5%8F%97%E6%83%A0ai%E4%BC%BA%E6%9C%8D%E5%99%A8-%E9%AB%98%E9%9A%8Epcb%E9%9C%80%E6%B1%82-010000430.html",
      "is_revenue": true,
      "source": "yahoo"
    },
    {
      "title": "驚！台股近一個月震盪上漲1.45% 、20檔主動式台股ETF僅1檔打敗大盤",
      "summary": "台股上半年狂牛行情大漲17000點後，7月進入上沖下洗行情，投信法人表示，投資人現階段，可以能因應市場而主動靈活選股策略的主動式台股ETF來介入台股較合宜。進一步觀察近一月大盤上漲1.45%，統計20檔主動式台股ETF中，僅主動群益台灣強棒（00982A）上漲2.3%打敗大盤。",
      "published": "07/11 00:46",
      "link": "https://tw.news.yahoo.com/%E9%A9%9A-%E5%8F%B0%E8%82%A1%E8%BF%91-%E5%80%8B%E6%9C%88%E9%9C%87%E7%9B%AA%E4%B8%8A%E6%BC%B21-45-20%E6%AA%94%E4%B8%BB%E5%8B%95%E5%BC%8F%E5%8F%B0%E8%82%A1etf%E5%83%851%E6%AA%94%E6%89%93%E6%95%97%E5%A4%A7%E7%9B%A4-004613797.html",
      "is_revenue": false,
      "source": "yahoo"
    },
    {
      "title": "聯發科6月營收衝今年新高！ASIC、手機拉貨雙引擎發威　達發同步寫佳績",
      "summary": "[FTNN新聞網]記者莊蕙如／綜合報導聯發科（2454）6月營運明顯升溫，單月合併營收580.12億元，不僅月增22.3%，也創下今年以來單月新高；旗下網通晶片廠達發同...",
      "published": "07/11 00:45",
      "link": "https://tw.stock.yahoo.com/news/%E8%81%AF%E7%99%BC%E7%A7%916%E6%9C%88%E7%87%9F%E6%94%B6%E8%A1%9D%E4%BB%8A%E5%B9%B4%E6%96%B0%E9%AB%98-asic-%E6%89%8B%E6%A9%9F%E6%8B%89%E8%B2%A8%E9%9B%99%E5%BC%95%E6%93%8E%E7%99%BC%E5%A8%81-%E9%81%94%E7%99%BC%E5%90%8C%E6%AD%A5%E5%AF%AB%E4%BD%B3%E7%B8%BE-004500691.html",
      "is_revenue": true,
      "source": "yahoo"
    },
    {
      "title": "聯發科Q2營收優於預期！AI ASIC第四季貢獻上看20億美元　法人看好毛利率、獲利再提升",
      "summary": "[FTNN新聞網]記者黃詩雯／綜合報導IC設計大廠聯發科（2454）10日公布6月營收，在智慧邊緣平台需求帶動下，單月與第二季業績皆優於市場預期，其中，第二季合併...",
      "published": "07/11 00:30",
      "link": "https://tw.stock.yahoo.com/news/%E8%81%AF%E7%99%BC%E7%A7%91q2%E7%87%9F%E6%94%B6%E5%84%AA%E6%96%BC%E9%A0%90%E6%9C%9F-ai-asic%E7%AC%AC%E5%9B%9B%E5%AD%A3%E8%B2%A2%E7%8D%BB%E4%B8%8A%E7%9C%8B20%E5%84%84%E7%BE%8E%E5%85%83-%E6%B3%95%E4%BA%BA%E7%9C%8B%E5%A5%BD%E6%AF%9B%E5%88%A9%E7%8E%87-%E7%8D%B2%E5%88%A9%E5%86%8D%E6%8F%90%E5%8D%87-003000903.html",
      "is_revenue": true,
      "source": "yahoo"
    },
    {
      "title": "SK海力士掛牌大漲　美股道瓊漲149點、台積電ADR跌0.65%",
      "summary": "人工智慧(AI) 投資熱潮持續席捲全球科技產業，美國股市受到大型科技股的提振，主要指數週五全部上漲，道瓊工業指數上漲149.60點，漲幅為0.29%，標準普爾500指數上漲0.42%，那斯達克指數上漲",
      "published": "07/11 00:08",
      "link": "https://tw.news.yahoo.com/sk%E6%B5%B7%E5%8A%9B%E5%A3%AB%E6%8E%9B%E7%89%8C%E5%A4%A7%E6%BC%B2-%E7%BE%8E%E8%82%A1%E9%81%93%E7%93%8A%E6%BC%B2149%E9%BB%9E-%E5%8F%B0%E7%A9%8D%E9%9B%BBadr%E8%B7%8C0-65-000826130.html",
      "is_revenue": false,
      "source": "yahoo"
    },
    {
      "title": "2Q、上半年營收齊創同期高！大廠搶攻高科技建築商機　3大業務同步成長",
      "summary": "受惠於新梯（含汰舊換新）業務出貨動能穩健成長。崇友實業（4506）公布2026年6月合併營收達5.01億元，年增12.28％，創歷年同期次高；2026年第二季合併營收15.76億元，年增5.30％；累計2026年上半年合併營收33.96億元，較去年同期成長9.89％，第二季及上半年營收雙雙改寫歷年同期新高。",
      "published": "07/11 00:05",
      "link": "https://tw.news.yahoo.com/2q-%E4%B8%8A%E5%8D%8A%E5%B9%B4%E7%87%9F%E6%94%B6%E9%BD%8A%E5%89%B5%E5%90%8C%E6%9C%9F%E9%AB%98-%E5%A4%A7%E5%BB%A0%E6%90%B6%E6%94%BB%E9%AB%98%E7%A7%91%E6%8A%80%E5%BB%BA%E7%AF%89%E5%95%86%E6%A9%9F-3%E5%A4%A7%E6%A5%AD%E5%8B%99%E5%90%8C%E6%AD%A5%E6%88%90%E9%95%B7-000500117.html",
      "is_revenue": true,
      "source": "yahoo"
    },
    {
      "title": "食安風暴擴大！南僑、泰山、福壽全遭重罰　回收範圍再擴大、Q3營運恐受衝擊",
      "summary": "[FTNN新聞網]記者莊蕙如／綜合報導南僑（1702）、泰山（1218）、福壽（1219）等食品業者，因中聯油脂沙拉油遭驗出一級致癌物「苯駢芘（BaP）」超標事件持續延...",
      "published": "07/10 23:50",
      "link": "https://tw.stock.yahoo.com/news/%E9%A3%9F%E5%AE%89%E9%A2%A8%E6%9A%B4%E6%93%B4%E5%A4%A7-%E5%8D%97%E5%83%91-%E6%B3%B0%E5%B1%B1-%E7%A6%8F%E5%A3%BD%E5%85%A8%E9%81%AD%E9%87%8D%E7%BD%B0-%E5%9B%9E%E6%94%B6%E7%AF%84%E5%9C%8D%E5%86%8D%E6%93%B4%E5%A4%A7-235000438.html",
      "is_revenue": false,
      "source": "yahoo"
    },
    {
      "title": "正二ETF教戰1／台股正二今年來全飆破120%　專家揭高勝率布局法",
      "summary": "AI牛市推動台股一路創高，讓追求高報酬的槓桿型ETF成為市場焦點。尤其今年來績效領先的00685L（群益臺灣加權正2）完成1拆24分割後，因入手門檻大幅降低，成為交易人氣王。究竟目前市場上4檔台股正二ETF投資人該怎麼挑？",
      "published": "07/10 23:30",
      "link": "https://tw.news.yahoo.com/%E6%AD%A3%E4%BA%8Cetf%E6%95%99%E6%88%B01-%E5%8F%B0%E8%82%A1%E6%AD%A3%E4%BA%8C%E4%BB%8A%E5%B9%B4%E4%BE%86%E5%85%A8%E9%A3%86%E7%A0%B4120-%E5%B0%88%E5%AE%B6%E6%8F%AD%E9%AB%98%E5%8B%9D%E7%8E%87%E5%B8%83%E5%B1%80%E6%B3%95-233001749.html",
      "is_revenue": false,
      "source": "yahoo"
    },
    {
      "title": "【9904 寶成】公告本公司之子公司裕元工業(集團)有限公司及 寶勝國際(控股)有限公司115年6月自結營收",
      "summary": "",
      "published": "07/10 17:02",
      "link": "https://mops.twse.com.tw/mops/#/web/t05sr01_1",
      "is_revenue": true,
      "source": "mops"
    },
    {
      "title": "【2454 聯發科】聯發科技115年6月份自結合併營收淨額公告",
      "summary": "",
      "published": "07/10 16:55",
      "link": "https://mops.twse.com.tw/mops/#/web/t05sr01_1",
      "is_revenue": true,
      "source": "mops"
    }
  ]
}